PythonKyber-1.0.2.dist-info/METADATA
PythonKyber-1.0.2.dist-info/WHEEL
PythonKyber/__init__.py
PythonKyber/__init__.pyi
PythonKyber/py.typed
PythonKyber/PythonKyber.cp312-win_amd64.pyd
PythonKyber-1.0.2.dist-info/RECORD
