Metadata-Version: 2.4
Name: PythonKyber
Version: 1.0.2
Summary: Python bindings for Kyber post-quantum cryptography using pqcrypto
Keywords: crypto,kyber,pqcrypto,post-quantum,python
Author: Konstantin Gorshkov <kostya_gorshkov_06@vk.com>, Rust pqcrypto Developers
Author-email: Konstantin Gorshkov <kostya_gorshkov_06@vk.com>, Rust pqcrypto Developers
License: MIT
Project-URL: Source Code, https://github.com/kostya2023/PythonKyber
